goodsync/__init__.py
goodsync/_GoodSync.cpython-310-aarch64-linux-gnu.so
goodsync.libs/libcrypto-13880bfc.so.1.0.2k
goodsync-0.0.6.dist-info/top_level.txt
goodsync-0.0.6.dist-info/METADATA
goodsync-0.0.6.dist-info/WHEEL
goodsync-0.0.6.dist-info/RECORD
goodsync-0.0.6.dist-info/LICENSE
