Metadata-Version: 2.1
Name: goodsync
Version: 0.0.6
Summary: Reverse engineering of GoodSync encrypted and decrypted file names
Home-page: https://github.com/bitjerry/goodsync
Author: Mr.lin
Author-email: adobe@outlook.my
License: Apache 2
Project-URL: GitHub: repo, https://github.com/bitjerry/goodsync/
Classifier: Development Status :: 5 - Production/Stable
Classifier: Intended Audience :: Developers
Classifier: License :: OSI Approved :: Apache Software License
Classifier: Operating System :: POSIX
Classifier: Operating System :: MacOS :: MacOS X
Classifier: Operating System :: Microsoft :: Windows
Classifier: Programming Language :: Python
Classifier: Programming Language :: Python :: 3
Classifier: Programming Language :: Python :: 3.8
Classifier: Programming Language :: Python :: 3.9
Classifier: Programming Language :: Python :: 3.10
Classifier: Programming Language :: Python :: 3.11
Classifier: Programming Language :: Python :: 3.12
Classifier: Topic :: Software Development :: Libraries
Classifier: Topic :: Security :: Cryptography
Requires-Python: >=3.8
License-File: LICENSE
